integrationsdk/__init__.py
integrationsdk/__main__.py
template/.DS_Store
template/__init__.py
template/cookiecutter.json
template/{{cookiecutter.integration_name}}/Makefile
template/{{cookiecutter.integration_name}}/__init__.py
template/{{cookiecutter.integration_name}}/main.py
template/{{cookiecutter.integration_name}}/requirements.txt
template/{{cookiecutter.integration_name}}/setup.py
template/{{cookiecutter.integration_name}}/{{cookiecutter.integration_name}}.py
template/{{cookiecutter.integration_name}}/app/__init__.py
template/{{cookiecutter.integration_name}}/docs/AUTHORS.rst
template/{{cookiecutter.integration_name}}/tests/test_{{cookiecutter.integration_name}}.py
integrationsdk-0.0.6.dist-info/LICENSE
integrationsdk-0.0.6.dist-info/METADATA
integrationsdk-0.0.6.dist-info/WHEEL
integrationsdk-0.0.6.dist-info/entry_points.txt
integrationsdk-0.0.6.dist-info/top_level.txt
integrationsdk-0.0.6.dist-info/zip-safe
integrationsdk-0.0.6.dist-info/RECORD
